[
  {
    "id": 1,
    "name": "Habitabilidad Ruido",
    "description": "Simulation of a program to determine the habitability of a building based on the levels and propagation of noise in the spaces mentioned.",
    "languages": [
      {
        "name": "Python",
        "icon": "icons/Python.svg"
      }
    ],
    "githubLink": "https://github.com/EngJuanSER/Habitabilidad-Ruido",
    "image": "images/grafoInicial.png"
  },
  {
    "id": 2,
    "name": "Data science explore",
    "description": "Approach to data science with exercises related to the use of python and useful libraries such as pandas.",
    "languages": [
      {
        "name": "Python",
        "icon": "icons/Python.svg"
      }
    ],
    "githubLink": "https://github.com/EngJuanSER/data-science"
  },
  {
    "id": 3,
    "name": "Pensieve",
    "description": "All-in-one desktop app for task management, document organization and Post-it style notes.",
    "languages": [
      {
        "name": "Python",
        "icon": "icons/Flutter.svg"
      }
    ],
    "githubLink": "https://github.com/EngJuanSER/Pensieve"
  }
]